{
    "bodies": {
        "candidate": [
            [
                0.502573753029915,
                0.31007894083925475
            ],
            [
                0.5127842678110767,
                0.6803802769027139
            ],
            [
                0.34737392835625935,
                0.6894562900415242
            ],
            [
                0.32082658992523927,
                1.0416055998273628
            ],
            [
                0.332058156184517,
                1.037975194571839
            ],
            [
                0.6781946072658939,
                0.6713042637639035
            ],
            [
                0.7108682545656109,
                1.037975194571839
            ],
            [
                0.672068298397197,
                1.0288991814330282
            ],
            [
                0.41374227443380945,
                1.0869856655214145
            ],
            [
                0.34839497983437545,
                0.7675100030352924
            ],
            [
                0.593447334582253,
                0.4934144062432221
            ],
            [
                0.6240788789257375,
                1.0833552602658898
            ],
            [
                0.804804990552297,
                0.7693252056630546
            ],
            [
                0.6240788789257375,
                1.2576147125310473
            ],
            [
                0.47194220868643033,
                0.26106846988967924
            ],
            [
                0.5342263488515158,
                0.26106846988967924
            ],
            [
                0.4341633039961326,
                0.32097015660582706
            ],
            [
                0.574047356498046,
                0.31733975135030285
            ]
        ],
        "subset": [
            [
                0.0,
                1.0,
                2.0,
                3.0,
                -1.0,
                5.0,
                6.0,
                -1.0,
                -1.0,
                -1.0,
                -1.0,
                -1.0,
                -1.0,
                -1.0,
                14.0,
                15.0,
                16.0,
                17.0
            ]
        ],
        "score": [
            [
                0.9475730061531067,
                1.0,
                0.9159042835235596,
                0.8792167901992798,
                0.2085346281528473,
                0.8726068139076233,
                0.8822113871574402,
                0.19692866504192352,
                0.19798165559768677,
                0.1378866732120514,
                0.0755365714430809,
                0.2993159592151642,
                0.0914924144744873,
                0.10357685387134552,
                0.9684021472930908,
                0.9815773963928223,
                0.9078050851821899,
                0.8992798328399658
            ]
        ]
    },
    "hands": [
        [
            [
                0.6700261954409645,
                1.0325295866885529
            ],
            [
                0.6700261954409645,
                1.023453573549742
            ],
            [
                0.6587946291816869,
                0.9998559393888358
            ],
            [
                0.6577735777035707,
                0.9708126973446427
            ],
            [
                0.6424578055318284,
                0.978073507855691
            ],
            [
                0.6557314747473384,
                0.990779926250025
            ],
            [
                0.6567525262254547,
                0.9944103315055497
            ],
            [
                0.63939465109748,
                0.990779926250025
            ],
            [
                0.6404157025755961,
                0.9962255341333113
            ],
            [
                0.6404157025755961,
                1.0125623577831697
            ],
            [
                0.6240788789257375,
                0.9962255341333113
            ],
            [
                0.6077420552758791,
                0.9889647236222634
            ],
            [
                0.6046789008415306,
                0.9871495209945012
            ],
            [
                0.6404157025755961,
                1.0288991814330282
            ],
            [
                0.6077420552758791,
                1.0307143840607904
            ],
            [
                0.6414367540537123,
                0.9962255341333113
            ],
            [
                0.6557314747473384,
                0.9944103315055497
            ],
            [
                0.6567525262254547,
                1.0397903971996005
            ],
            [
                0.6557314747473384,
                1.0288991814330282
            ],
            [
                0.6547104232692222,
                1.0180079656664558
            ],
            [
                0.6557314747473384,
                1.0016711420165973
            ]
        ],
        [
            [
                0.34124761948756244,
                1.0397903971996005
            ],
            [
                0.34022656800944623,
                1.0288991814330282
            ],
            [
                0.33410025914074926,
                1.0125623577831697
            ],
            [
                0.3422686709656785,
                0.9853343183667389
            ],
            [
                0.36064759757176934,
                0.9889647236222634
            ],
            [
                0.3943422963496025,
                1.0125623577831697
            ],
            [
                0.3923001933933702,
                1.0180079656664558
            ],
            [
                0.3923001933933702,
                0.9889647236222634
            ],
            [
                0.3943422963496025,
                0.990779926250025
            ],
            [
                0.36064759757176934,
                1.0252687761775043
            ],
            [
                0.39332124487148634,
                1.0180079656664558
            ],
            [
                0.39332124487148634,
                0.9835191157389773
            ],
            [
                0.42599489217120334,
                0.978073507855691
            ],
            [
                0.3943422963496025,
                1.0325295866885529
            ],
            [
                0.3943422963496025,
                1.0288991814330282
            ],
            [
                0.39332124487148634,
                0.9962255341333113
            ],
            [
                0.3923001933933702,
                0.9925951288777872
            ],
            [
                0.3943422963496025,
                1.0361599919440767
            ],
            [
                0.39332124487148634,
                1.0288991814330282
            ],
            [
                0.39332124487148634,
                1.0125623577831697
            ],
            [
                0.39332124487148634,
                1.0034863446443596
            ]
        ]
    ],
    "hands_score": [
        [
            0.186766117811203,
            0.17976893484592438,
            0.14807286858558655,
            0.16779714822769165,
            0.14654774963855743,
            0.1116156205534935,
            0.12226381152868271,
            0.12233781069517136,
            0.13352665305137634,
            0.11184994131326675,
            0.10602967441082001,
            0.10809347778558731,
            0.11522412300109863,
            0.11371735483407974,
            0.091642826795578,
            0.11275092512369156,
            0.12419357895851135,
            0.12959864735603333,
            0.1129378080368042,
            0.1155824288725853,
            0.1114160493016243
        ],
        [
            0.19567520916461945,
            0.18672768771648407,
            0.16173158586025238,
            0.1664118617773056,
            0.1430557519197464,
            0.09697936475276947,
            0.11356303095817566,
            0.11452868580818176,
            0.10844923555850983,
            0.1125267818570137,
            0.10472950339317322,
            0.11452946066856384,
            0.1152086853981018,
            0.11375340074300766,
            0.09606277942657471,
            0.11437173187732697,
            0.1349380612373352,
            0.11775714159011841,
            0.12101857364177704,
            0.12383021414279938,
            0.12211857736110687
        ]
    ],
    "faces": [
        [
            [
                0.4382475099085972,
                0.2792204961672997
            ],
            [
                0.4382475099085972,
                0.31370934609477863
            ],
            [
                0.4402896128648296,
                0.34275258813897175
            ],
            [
                0.44335276729917805,
                0.3754262354386887
            ],
            [
                0.4484580246897587,
                0.4044694774828815
            ],
            [
                0.4596895909490365,
                0.4298823142715503
            ],
            [
                0.47194220868643033,
                0.44984954317693276
            ],
            [
                0.4882790323362888,
                0.4625559615712674
            ],
            [
                0.5056369074642635,
                0.46618636682679127
            ],
            [
                0.5240158340703543,
                0.4607407589435051
            ],
            [
                0.5393316062420966,
                0.4462191379214089
            ],
            [
                0.5505631725013744,
                0.4262519090160261
            ],
            [
                0.560773687282536,
                0.40083907222735726
            ],
            [
                0.5658789446731167,
                0.37361103281092645
            ],
            [
                0.5689420991074652,
                0.34093738551120945
            ],
            [
                0.5699631505855813,
                0.3118941434670167
            ],
            [
                0.5699631505855813,
                0.27740529353953775
            ],
            [
                0.4484580246897587,
                0.24654684886758269
            ],
            [
                0.4576474879928041,
                0.23565563310101034
            ],
            [
                0.4688790542520819,
                0.2302100252177242
            ],
            [
                0.48011062051135966,
                0.23202522784548615
            ],
            [
                0.4903211352925212,
                0.23565563310101034
            ],
            [
                0.515847422245425,
                0.23565563310101034
            ],
            [
                0.5260579370265868,
                0.2302100252177242
            ],
            [
                0.5372895032858642,
                0.2302100252177242
            ],
            [
                0.548521069545142,
                0.2338404304732484
            ],
            [
                0.5587315843263037,
                0.24473164623982074
            ],
            [
                0.502573753029915,
                0.2628836725174412
            ],
            [
                0.502573753029915,
                0.28103569879506163
            ],
            [
                0.502573753029915,
                0.29737252244492013
            ],
            [
                0.502573753029915,
                0.3155245487225409
            ],
            [
                0.4882790323362888,
                0.33912218288344753
            ],
            [
                0.49542639268310196,
                0.33912218288344753
            ],
            [
                0.502573753029915,
                0.34093738551120945
            ],
            [
                0.5107421648548444,
                0.33912218288344753
            ],
            [
                0.5178895252016574,
                0.3373069802556855
            ],
            [
                0.4596895909490365,
                0.26651407777296543
            ],
            [
                0.46785800277396583,
                0.25743806463415503
            ],
            [
                0.47806851755512725,
                0.25743806463415503
            ],
            [
                0.4862369293800566,
                0.26651407777296543
            ],
            [
                0.4770474660770112,
                0.27195968565625156
            ],
            [
                0.46785800277396583,
                0.27195968565625156
            ],
            [
                0.5199316281578896,
                0.26651407777296543
            ],
            [
                0.5281000399828188,
                0.25562286200639306
            ],
            [
                0.5383105547639805,
                0.25562286200639306
            ],
            [
                0.5475000180670259,
                0.2646988751452032
            ],
            [
                0.5383105547639805,
                0.2701444830284893
            ],
            [
                0.529121091460935,
                0.2701444830284893
            ],
            [
                0.47602641459889494,
                0.37905664069421263
            ],
            [
                0.4862369293800566,
                0.36998062755540256
            ],
            [
                0.4984895471174504,
                0.3645350196721164
            ],
            [
                0.5035948045080311,
                0.3645350196721164
            ],
            [
                0.5097211133767281,
                0.3645350196721164
            ],
            [
                0.5209526796360059,
                0.36635022229987835
            ],
            [
                0.5321842458952837,
                0.3754262354386887
            ],
            [
                0.5240158340703543,
                0.38268704594973685
            ],
            [
                0.5138053192891928,
                0.388132653833023
            ],
            [
                0.5046158559861474,
                0.39176305908854725
            ],
            [
                0.4944053412049857,
                0.3899478564607849
            ],
            [
                0.48419482642382417,
                0.386317451205261
            ],
            [
                0.47806851755512725,
                0.37905664069421263
            ],
            [
                0.49134218677063723,
                0.3754262354386887
            ],
            [
                0.5035948045080311,
                0.3754262354386887
            ],
            [
                0.5168684737235413,
                0.3754262354386887
            ],
            [
                0.529121091460935,
                0.3754262354386887
            ],
            [
                0.5168684737235413,
                0.3754262354386887
            ],
            [
                0.5035948045080311,
                0.3754262354386887
            ],
            [
                0.49134218677063723,
                0.3772414380664506
            ]
        ]
    ],
    "faces_score": [
        [
            0.9070662260055542,
            0.9371075630187988,
            0.9327155947685242,
            0.9489085078239441,
            0.9698746800422668,
            0.9434524774551392,
            0.9435160160064697,
            0.9474427103996277,
            0.9475752115249634,
            0.9203824400901794,
            0.9461969137191772,
            0.9328958988189697,
            0.9687169194221497,
            0.9288589358329773,
            0.9212933778762817,
            0.9275910258293152,
            0.8949249386787415,
            0.9815719723701477,
            0.9846847653388977,
            0.9574697613716125,
            0.964833676815033,
            0.9587509036064148,
            0.9537264108657837,
            0.9658887386322021,
            0.9892245531082153,
            1.0004123449325562,
            0.9920238852500916,
            1.024654507637024,
            0.9945363998413086,
            0.9957478642463684,
            0.9727301001548767,
            0.9585700035095215,
            0.9758630990982056,
            0.9699470400810242,
            0.9655524492263794,
            0.9554957151412964,
            0.9968265295028687,
            0.9712294936180115,
            0.9635807275772095,
            0.9772626161575317,
            0.9552215337753296,
            0.9588215947151184,
            0.9755690097808838,
            0.9786298274993896,
            0.9933825731277466,
            1.0325710773468018,
            0.9983692765235901,
            0.9803591966629028,
            0.9483121633529663,
            0.9454501867294312,
            0.9436458945274353,
            0.9453262090682983,
            0.9458669424057007,
            0.956473171710968,
            0.9630652070045471,
            0.9686951041221619,
            0.9616261720657349,
            0.9794043302536011,
            0.9698875546455383,
            0.9698784351348877,
            0.9560310244560242,
            0.9591653347015381,
            0.9613024592399597,
            0.9445808529853821,
            0.9631443619728088,
            0.9501511454582214,
            0.9677536487579346,
            0.9629403352737427
        ]
    ]
}