{
    "bodies": {
        "candidate": [
            [
                0.5002936911758541,
                0.30727072952392126
            ],
            [
                0.5128537944234026,
                0.6797196578245631
            ],
            [
                0.34957245220527056,
                0.6895444496982013
            ],
            [
                0.3214378209307616,
                1.0414506313539635
            ],
            [
                0.3345003283082122,
                1.0432369571491704
            ],
            [
                0.6761351366415348,
                0.6698948659509251
            ],
            [
                0.7082890009552592,
                1.0396643055587564
            ],
            [
                0.6691014788229075,
                1.0343053281731358
            ],
            [
                0.41488498909252336,
                1.0807497988485157
            ],
            [
                0.35158206872487835,
                0.7663564588920986
            ],
            [
                0.5927360510778119,
                0.5198434991535443
            ],
            [
                0.6228802988719286,
                1.0807497988485157
            ],
            [
                0.6670918623032998,
                0.1875869012450579
            ],
            [
                0.637952422768987,
                0.5770059246001655
            ],
            [
                0.47014944338173725,
                0.2608262588485414
            ],
            [
                0.5314427472297747,
                0.25903993305333456
            ],
            [
                0.43397634602879726,
                0.3251339874759903
            ],
            [
                0.5726398858817341,
                0.31798868429516275
            ]
        ],
        "subset": [
            [
                0.0,
                1.0,
                2.0,
                3.0,
                -1.0,
                5.0,
                6.0,
                -1.0,
                -1.0,
                -1.0,
                -1.0,
                11.0,
                -1.0,
                -1.0,
                14.0,
                15.0,
                16.0,
                17.0
            ]
        ],
        "score": [
            [
                0.993996262550354,
                1.0,
                0.9614884853363037,
                0.9351548552513123,
                0.22348766028881073,
                0.9275226593017578,
                0.9261941313743591,
                0.21390248835086823,
                0.23149240016937256,
                0.13100937008857727,
                0.08160474896430969,
                0.3597312569618225,
                0.13203220069408417,
                0.0970003679394722,
                0.9833068251609802,
                0.9959582686424255,
                0.9330194592475891,
                0.9311937093734741
            ]
        ]
    },
    "hands": [
        [
            [
                0.6680966705631036,
                1.0378779797635493
            ],
            [
                0.6680966705631036,
                1.027160024992308
            ],
            [
                0.6570437797052608,
                1.011083092835446
            ],
            [
                0.656038971445457,
                0.9807155543169283
            ],
            [
                0.6409668475483987,
                0.9842882059073425
            ],
            [
                0.6550341631856531,
                0.9914335090881699
            ],
            [
                0.6550341631856531,
                1.011083092835446
            ],
            [
                0.637952422768987,
                0.9967924864737904
            ],
            [
                0.6389572310287908,
                1.011083092835446
            ],
            [
                0.6389572310287908,
                1.0146557444258597
            ],
            [
                0.6228802988719286,
                1.011083092835446
            ],
            [
                0.6218754906121247,
                0.9860745317025491
            ],
            [
                0.6047937501954586,
                0.9860745317025491
            ],
            [
                0.6399620392885947,
                1.0307326765827218
            ],
            [
                0.6389572310287908,
                1.0343053281731358
            ],
            [
                0.6540293549258491,
                1.0146557444258597
            ],
            [
                0.6550341631856531,
                0.9967924864737904
            ],
            [
                0.6550341631856531,
                1.0432369571491704
            ],
            [
                0.6540293549258491,
                1.0307326765827218
            ],
            [
                0.6530245466660454,
                1.0253736991971014
            ],
            [
                0.6550341631856531,
                1.023587373401894
            ]
        ],
        [
            [
                0.3445484109062511,
                1.0432369571491704
            ],
            [
                0.34354360264644723,
                1.027160024992308
            ],
            [
                0.34354360264644723,
                1.011083092835446
            ],
            [
                0.34655802742585884,
                0.9860745317025491
            ],
            [
                0.36363976784252494,
                0.9842882059073425
            ],
            [
                0.3967984404160534,
                1.0128694186306526
            ],
            [
                0.3947888238964456,
                1.0200147218114803
            ],
            [
                0.3947888238964456,
                0.987860857497756
            ],
            [
                0.3957936321562495,
                0.9896471832929626
            ],
            [
                0.36363976784252494,
                1.023587373401894
            ],
            [
                0.3957936321562495,
                1.0200147218114803
            ],
            [
                0.3957936321562495,
                0.9860745317025491
            ],
            [
                0.3967984404160534,
                0.9842882059073425
            ],
            [
                0.3967984404160534,
                1.0343053281731358
            ],
            [
                0.3967984404160534,
                1.0307326765827218
            ],
            [
                0.3957936321562495,
                1.0200147218114803
            ],
            [
                0.3947888238964456,
                0.9914335090881699
            ],
            [
                0.3967984404160534,
                1.0343053281731358
            ],
            [
                0.3957936321562495,
                1.0325190023779292
            ],
            [
                0.3957936321562495,
                1.0200147218114803
            ],
            [
                0.3957936321562495,
                1.023587373401894
            ]
        ]
    ],
    "hands_score": [
        [
            0.20926077663898468,
            0.19739988446235657,
            0.16465279459953308,
            0.1811671257019043,
            0.16430585086345673,
            0.12354501336812973,
            0.13260933756828308,
            0.13689808547496796,
            0.14722754061222076,
            0.12384742498397827,
            0.11440104246139526,
            0.11623737961053848,
            0.122386634349823,
            0.127011239528656,
            0.10265470296144485,
            0.12904952466487885,
            0.13953237235546112,
            0.14352796971797943,
            0.1261739879846573,
            0.128038689494133,
            0.12644004821777344
        ],
        [
            0.2077765166759491,
            0.19276919960975647,
            0.16503316164016724,
            0.16959138214588165,
            0.15884867310523987,
            0.10836119204759598,
            0.12393717467784882,
            0.12841328978538513,
            0.12385883927345276,
            0.12377090752124786,
            0.11723905056715012,
            0.12592670321464539,
            0.1252128630876541,
            0.12417995929718018,
            0.11040735244750977,
            0.12932142615318298,
            0.15094038844108582,
            0.1297355443239212,
            0.13470359146595,
            0.13809500634670258,
            0.13904131948947906
        ]
    ],
    "faces": [
        [
            [
                0.43699077080820903,
                0.2822621683910244
            ],
            [
                0.43699077080820903,
                0.3162023584999558
            ],
            [
                0.43900038732781677,
                0.3465698970184734
            ],
            [
                0.44301962036703224,
                0.37693743553699094
            ],
            [
                0.4480436616660517,
                0.40551864826030154
            ],
            [
                0.4590965525238946,
                0.42874088359799145
            ],
            [
                0.47115425164154123,
                0.4483904673452676
            ],
            [
                0.48723118379840347,
                0.4591084221165091
            ],
            [
                0.5053177324748734,
                0.460894747911716
            ],
            [
                0.5223994728915397,
                0.45553577052609534
            ],
            [
                0.5374715967885979,
                0.4430314899596468
            ],
            [
                0.5485244876464408,
                0.4233819062123708
            ],
            [
                0.5595773785042836,
                0.3983733450794739
            ],
            [
                0.5635966115434992,
                0.3733647839465771
            ],
            [
                0.5666110363229108,
                0.3412109196328526
            ],
            [
                0.5676158445827146,
                0.3108433811143352
            ],
            [
                0.5676158445827146,
                0.27868951680061066
            ],
            [
                0.4470388534062478,
                0.2465356524868862
            ],
            [
                0.45608212774448287,
                0.23403137192043766
            ],
            [
                0.4661302103425218,
                0.2304587203300238
            ],
            [
                0.47718310120036456,
                0.2304587203300238
            ],
            [
                0.48723118379840347,
                0.23403137192043766
            ],
            [
                0.5123513902935006,
                0.23224504612523073
            ],
            [
                0.5234042811513435,
                0.22867239453481686
            ],
            [
                0.5344571720091864,
                0.2268860687396101
            ],
            [
                0.5455100628670291,
                0.2304587203300238
            ],
            [
                0.555558145465068,
                0.24296300089647233
            ],
            [
                0.5002936911758541,
                0.2608262588485414
            ],
            [
                0.5002936911758541,
                0.27868951680061066
            ],
            [
                0.5002936911758541,
                0.29476644895747295
            ],
            [
                0.5002936911758541,
                0.3108433811143352
            ],
            [
                0.4862263755385996,
                0.3358519422472319
            ],
            [
                0.4932600333572268,
                0.3358519422472319
            ],
            [
                0.501298499435658,
                0.3358519422472319
            ],
            [
                0.5083321572542852,
                0.334065616452025
            ],
            [
                0.5153658150729123,
                0.334065616452025
            ],
            [
                0.45809174426409066,
                0.2679715620293691
            ],
            [
                0.4661302103425218,
                0.25725360725812746
            ],
            [
                0.4761782929405607,
                0.25725360725812746
            ],
            [
                0.4842167590189918,
                0.2661852362341622
            ],
            [
                0.47517348468075676,
                0.2715442136197829
            ],
            [
                0.4661302103425218,
                0.2715442136197829
            ],
            [
                0.5173754315925201,
                0.2661852362341622
            ],
            [
                0.5254138976709513,
                0.25368095566771376
            ],
            [
                0.5354619802689902,
                0.25368095566771376
            ],
            [
                0.5445052546072251,
                0.26439891043895525
            ],
            [
                0.5354619802689902,
                0.26975788782457605
            ],
            [
                0.5264187059307552,
                0.26975788782457605
            ],
            [
                0.47517348468075676,
                0.37693743553699094
            ],
            [
                0.48522156727879573,
                0.36621948076574945
            ],
            [
                0.4962744581366385,
                0.36086050338012865
            ],
            [
                0.5023033076954618,
                0.36086050338012865
            ],
            [
                0.5073273489944813,
                0.3590741775849219
            ],
            [
                0.5193850481121279,
                0.3626468291753356
            ],
            [
                0.5294331307101668,
                0.37157845815137025
            ],
            [
                0.5213946646317358,
                0.3787237613321979
            ],
            [
                0.5113465820336969,
                0.38229641292261174
            ],
            [
                0.5023033076954618,
                0.3840827387178187
            ],
            [
                0.4932600333572268,
                0.3840827387178187
            ],
            [
                0.4842167590189918,
                0.38229641292261174
            ],
            [
                0.4781879094601685,
                0.37693743553699094
            ],
            [
                0.4902456085778151,
                0.3733647839465771
            ],
            [
                0.5023033076954618,
                0.37157845815137025
            ],
            [
                0.5143610068131085,
                0.3697921323561632
            ],
            [
                0.527423514190559,
                0.37157845815137025
            ],
            [
                0.5143610068131085,
                0.3697921323561632
            ],
            [
                0.5023033076954618,
                0.3697921323561632
            ],
            [
                0.4902456085778151,
                0.3733647839465771
            ]
        ]
    ],
    "faces_score": [
        [
            0.901911735534668,
            0.9379792809486389,
            0.9297668933868408,
            0.9462673664093018,
            0.980714738368988,
            0.9422089457511902,
            0.9612219929695129,
            0.9287975430488586,
            0.9298221468925476,
            0.9115524888038635,
            0.9629471302032471,
            0.9317967295646667,
            0.9777382016181946,
            0.9298331141471863,
            0.9317640662193298,
            0.9356157779693604,
            0.9016873240470886,
            0.9895500540733337,
            0.9985707998275757,
            0.9791220426559448,
            0.9745321869850159,
            0.95927494764328,
            0.9677033424377441,
            0.9748906493186951,
            0.9936231374740601,
            1.0074020624160767,
            1.0030546188354492,
            1.004377841949463,
            1.0093787908554077,
            0.9915732145309448,
            0.9780701994895935,
            0.9757195711135864,
            0.9895905256271362,
            0.9859445691108704,
            0.9868195652961731,
            0.9741427898406982,
            1.0128695964813232,
            0.9712697267532349,
            0.9507781267166138,
            0.9838054776191711,
            0.9752549529075623,
            0.9891397953033447,
            0.9816423654556274,
            0.9689908027648926,
            0.9874547123908997,
            1.0235388278961182,
            1.0117970705032349,
            0.9917657971382141,
            0.9492380023002625,
            0.9595009088516235,
            0.9689279794692993,
            0.9725236892700195,
            0.9810499548912048,
            0.9830424189567566,
            0.9559780955314636,
            0.9594229459762573,
            0.9718392491340637,
            0.9881815314292908,
            0.97072833776474,
            0.9748263955116272,
            0.9545146226882935,
            0.9578608274459839,
            0.9627041220664978,
            0.952471137046814,
            0.9546032547950745,
            0.9607955813407898,
            0.9706953167915344,
            0.9603531956672668
        ]
    ]
}